rlenvs/__init__.py
rlenvs/bandits/__init__.py
rlenvs/bandits/bandits.py
rlenvs/mdps/__init__.py
rlenvs/mdps/balanced_trees.py
rlenvs/utils/__init__.py
rlenvs/utils/base_environment.py
rlenvs/utils/maths_utils.py
rlenvs/utils/tree_utils.py
rlenvs-0.0.0.2.dist-info/METADATA
rlenvs-0.0.0.2.dist-info/RECORD
rlenvs-0.0.0.2.dist-info/WHEEL
rlenvs-0.0.0.2.dist-info/top_level.txt
