Metadata-Version: 2.1
Name: rlenvs
Version: 0.0.0.2
Summary: Reinforcment Learning Environments
Home-page: https://github.com/ai-nikolai/rl-environments
Author: nikolai rozanov
Author-email: nikolai.rozanov@gmail.com
License: Apache 2.0
Platform: UNKNOWN
Requires-Python: >=3.6
Requires-Dist: numpy
Requires-Dist: matplotlib
Requires-Dist: seaborn (>=0.9)
Requires-Dist: networkx
Requires-Dist: pygraphviz
